geosat/__init__.py
geosat/read_write_img.py
geosat-0.0.1.dist-info/METADATA
geosat-0.0.1.dist-info/WHEEL
geosat-0.0.1.dist-info/top_level.txt
geosat-0.0.1.dist-info/RECORD
